entanglement_engine/__init__.py
entanglement_engine/cli.py
entanglement_engine/core.py
entanglement_engine/simulate.py
entanglement_engine-0.1.0.dist-info/METADATA
entanglement_engine-0.1.0.dist-info/WHEEL
entanglement_engine-0.1.0.dist-info/entry_points.txt
entanglement_engine-0.1.0.dist-info/licenses/LICENSE
entanglement_engine-0.1.0.dist-info/RECORD
