Metadata-Version: 2.4
Name: entanglement-engine
Version: 0.1.0
Summary: Geometric quantum coherence where entanglement is the ground state
Project-URL: Homepage, https://github.com/worldbridgerstudios/EntanglementEngine
Project-URL: Documentation, https://github.com/worldbridgerstudios/EntanglementEngine
Project-URL: Repository, https://github.com/worldbridgerstudios/EntanglementEngine
Author-email: Nicholas David Brown <worldbridgerstudios@gmail.com>
License-Expression: CC0-1.0
License-File: LICENSE
Keywords: coherence,entanglement,error-correction,geometry,kuramoto,physics,quantum,synchronization
Classifier: Development Status :: 4 - Beta
Classifier: Intended Audience :: Science/Research
Classifier: Programming Language :: Python :: 3
Classifier: Programming Language :: Python :: 3.9
Classifier: Programming Language :: Python :: 3.10
Classifier: Programming Language :: Python :: 3.11
Classifier: Programming Language :: Python :: 3.12
Classifier: Topic :: Scientific/Engineering :: Physics
Requires-Python: >=3.9
Requires-Dist: numpy>=1.20.0
